isar/__init__.py
isar/modules.py
isar/script.py
isar/apis/__init__.py
isar/apis/api.py
isar/apis/models/__init__.py
isar/apis/models/models.py
isar/apis/models/start_mission_definition.py
isar/apis/robot_control/robot_controller.py
isar/apis/schedule/__init__.py
isar/apis/schedule/scheduling_controller.py
isar/apis/security/__init__.py
isar/apis/security/authentication.py
isar/config/__init__.py
isar/config/log.py
isar/config/logging.conf
isar/config/open_telemetry.py
isar/config/settings.py
isar/config/certs/ca-cert.pem
isar/config/keyvault/__init__.py
isar/config/keyvault/keyvault_service.py
isar/config/maps/JSP1_intermediate_deck.json
isar/config/maps/JSP1_weather_deck.json
isar/config/maps/default_map.json
isar/config/maps/klab_b.json
isar/config/maps/klab_compressor.json
isar/config/maps/klab_turtlebot.json
isar/config/maps/turtleworld.json
isar/eventhandlers/eventhandler.py
isar/models/__init__.py
isar/models/events.py
isar/models/status.py
isar/robot/robot.py
isar/robot/robot_battery.py
isar/robot/robot_monitor_mission.py
isar/robot/robot_pause_mission.py
isar/robot/robot_resume_mission.py
isar/robot/robot_start_mission.py
isar/robot/robot_status.py
isar/robot/robot_stop_mission.py
isar/robot/robot_upload_inspection.py
isar/services/__init__.py
isar/services/service_connections/__init__.py
isar/services/service_connections/persistent_memory.py
isar/services/service_connections/mqtt/__init__.py
isar/services/service_connections/mqtt/mqtt_client.py
isar/services/service_connections/mqtt/robot_heartbeat_publisher.py
isar/services/service_connections/mqtt/robot_info_publisher.py
isar/services/utilities/__init__.py
isar/services/utilities/mqtt_utilities.py
isar/services/utilities/robot_utilities.py
isar/services/utilities/scheduling_utilities.py
isar/state_machine/__init__.py
isar/state_machine/state_machine.py
isar/state_machine/states_enum.py
isar/state_machine/states/__init__.py
isar/state_machine/states/await_next_mission.py
isar-1.34.17.dist-info/licenses/LICENSE
isar-1.34.17.dist-info/METADATA
isar-1.34.17.dist-info/WHEEL
isar-1.34.17.dist-info/entry_points.txt
isar-1.34.17.dist-info/top_level.txt
isar-1.34.17.dist-info/RECORD
