Metadata-Version: 2.4
Name: isar
Version: 1.34.17
Summary: Integration and Supervisory control of Autonomous Robots
Author-email: Equinor ASA <fg_robots_dev@equinor.com>
License: Eclipse Public License version 2.0
Project-URL: repository, https://github.com/equinor/isar.git
Classifier: Intended Audience :: Developers
Classifier: Intended Audience :: Science/Research
Classifier: License :: OSI Approved :: Eclipse Public License 2.0 (EPL-2.0)
Classifier: Natural Language :: English
Classifier: Programming Language :: Python :: 3
Classifier: Programming Language :: Python :: 3.9
Classifier: Programming Language :: Python :: 3.10
Classifier: Programming Language :: Python :: 3.11
Classifier: Programming Language :: Python :: 3.12
Classifier: Programming Language :: Python :: 3.13
Classifier: Topic :: Scientific/Engineering
Classifier: Topic :: Scientific/Engineering :: Physics
Classifier: Topic :: Software Development :: Libraries
Requires-Python: >=3.9
License-File: LICENSE
Requires-Dist: alitra>=1.1.3
Requires-Dist: azure-identity
Requires-Dist: azure-keyvault-secrets
Requires-Dist: azure-storage-blob
Requires-Dist: backoff
Requires-Dist: click
Requires-Dist: dacite
Requires-Dist: fastapi-azure-auth
Requires-Dist: fastapi>=0.121.0
Requires-Dist: dependency-injector
Requires-Dist: numpy
Requires-Dist: paho-mqtt
Requires-Dist: pydantic_settings
Requires-Dist: pydantic
Requires-Dist: PyJWT
Requires-Dist: python-dotenv
Requires-Dist: PyYAML
Requires-Dist: requests-toolbelt
Requires-Dist: requests
Requires-Dist: starlette>=0.49.1
Requires-Dist: transitions
Requires-Dist: uvicorn
Requires-Dist: opentelemetry-api==1.38.0
Requires-Dist: opentelemetry-sdk
Requires-Dist: opentelemetry-exporter-otlp
Requires-Dist: opentelemetry-instrumentation-fastapi
Requires-Dist: azure-monitor-opentelemetry
Requires-Dist: azure-monitor-opentelemetry-exporter
Requires-Dist: pymysql
Requires-Dist: sqlalchemy
Requires-Dist: psycopg2-binary
Provides-Extra: dev
Requires-Dist: black; extra == "dev"
Requires-Dist: isort; extra == "dev"
Requires-Dist: mypy; extra == "dev"
Requires-Dist: pip-tools; extra == "dev"
Requires-Dist: pre-commit; extra == "dev"
Requires-Dist: pytest-mock; extra == "dev"
Requires-Dist: pytest-xdist; extra == "dev"
Requires-Dist: pytest; extra == "dev"
Requires-Dist: requests-mock; extra == "dev"
Requires-Dist: ruff; extra == "dev"
Requires-Dist: testcontainers[mysql]; extra == "dev"
Requires-Dist: alembic; extra == "dev"
Dynamic: license-file
